CHANGES.md
LICENSE
MANIFEST.in
README.md
setup.py
monitor_mysql_overflows/SchemaInformation.py
monitor_mysql_overflows/__init__.py
monitor_mysql_overflows.egg-info/PKG-INFO
monitor_mysql_overflows.egg-info/SOURCES.txt
monitor_mysql_overflows.egg-info/dependency_links.txt
monitor_mysql_overflows.egg-info/entry_points.txt
monitor_mysql_overflows.egg-info/requires.txt
monitor_mysql_overflows.egg-info/top_level.txt