Metadata-Version: 1.1
Name: monitor-mysql-overflows
Version: 1.1.1
Summary: MySQL utilities to detect integer like columns overflows
Home-page: http://www.rentabiliweb-group.com
Author: Jeremy Cohen Solal
Author-email: jeremy@rentabiliweb.com
License: Proprietary
Platform: UNKNOWN
Classifier: Intended Audience :: System Administrators
Classifier: Operating System :: OS Independent
Classifier: Programming Language :: Python :: 2
Classifier: Topic :: Database :: Database Engines/Servers
Classifier: Topic :: System :: Monitoring
Classifier: Topic :: Utilities
